README.md
setup.cfg
setup.py
cryptoportfolio/__init__.py
cryptoportfolio/main.py
cryptoportfolio.egg-info/PKG-INFO
cryptoportfolio.egg-info/SOURCES.txt
cryptoportfolio.egg-info/dependency_links.txt
cryptoportfolio.egg-info/entry_points.txt
cryptoportfolio.egg-info/requires.txt
cryptoportfolio.egg-info/top_level.txt
cryptoportfolio/cli/__init__.py
cryptoportfolio/cli/printers.py
cryptoportfolio/interfaces/__init__.py
cryptoportfolio/interfaces/base.py
cryptoportfolio/interfaces/exchanges/__init__.py
cryptoportfolio/interfaces/exchanges/binance.py
cryptoportfolio/interfaces/exchanges/bittrex.py
cryptoportfolio/interfaces/exchanges/poloniex.py
cryptoportfolio/interfaces/miningpools/__init__.py
cryptoportfolio/interfaces/miningpools/f2pool.py
cryptoportfolio/interfaces/miningpools/nicehash.py
cryptoportfolio/interfaces/miningpools/pool_bitcoin_com.py
cryptoportfolio/interfaces/wallets/__init__.py
cryptoportfolio/interfaces/wallets/bitcoin.py
cryptoportfolio/interfaces/wallets/cardano.py
cryptoportfolio/interfaces/wallets/crds.py
cryptoportfolio/interfaces/wallets/emercoin.py
cryptoportfolio/interfaces/wallets/ethereum.py
cryptoportfolio/interfaces/wallets/hyperstake.py
cryptoportfolio/interfaces/wallets/magi.py
cryptoportfolio/interfaces/wallets/nem.py
cryptoportfolio/interfaces/wallets/qtum.py
cryptoportfolio/interfaces/wallets/radium.py
cryptoportfolio/interfaces/wallets/reddcoin.py
cryptoportfolio/interfaces/wallets/stellar.py
cryptoportfolio/lib/__init__.py
cryptoportfolio/lib/bittrex.py
cryptoportfolio/lib/convert/__init__.py
cryptoportfolio/lib/convert/coinmarketcap.py
cryptoportfolio/lib/convert/cryptocompare.py
cryptoportfolio/utils/__init__.py
cryptoportfolio/utils/io.py