Metadata-Version: 1.1
Name: cryptoportfolio
Version: 0.3.8
Summary: Show your coins portfolio
Home-page: https://github.com/a1fred/cryptoportfolio
Author: a1fred
Author-email: demalf@gmail.com
License: MIT
Platform: UNKNOWN
Classifier: Topic :: Office/Business :: Financial
Classifier: Environment :: Console
Classifier: Operating System :: POSIX :: Linux
Classifier: Operating System :: MacOS :: MacOS X
Classifier: Development Status :: 4 - Beta
Classifier: Programming Language :: Python :: 2.7
Classifier: Programming Language :: Python :: 3.5
Classifier: Programming Language :: Python :: 3.6
